anirban/__init__.py
anirban-0.1.0.dist-info/LICENSE
anirban-0.1.0.dist-info/METADATA
anirban-0.1.0.dist-info/WHEEL
anirban-0.1.0.dist-info/top_level.txt
anirban-0.1.0.dist-info/RECORD
